{
  "name": "2025-09-15 (easy)",
  "dominoes": [
    [
      1,
      0
    ],
    [
      1,
      5
    ],
    [
      4,
      4
    ],
    [
      3,
      0
    ]
  ],
  "regions": [
    {
      "indices": [
        [
          0,
          0
        ]
      ],
      "type": "sum",
      "target": 1
    },
    {
      "indices": [
        [
          0,
          1
        ],
        [
          0,
          2
        ]
      ],
      "type": "sum",
      "target": 9
    },
    {
      "indices": [
        [
          0,
          3
        ],
        [
          0,
          4
        ]
      ],
      "type": "sum",
      "target": 4
    },
    {
      "indices": [
        [
          0,
          5
        ],
        [
          0,
          6
        ]
      ],
      "type": "sum",
      "target": 3
    },
    {
      "indices": [
        [
          0,
          7
        ]
      ],
      "type": "empty"
    }
  ],
  "solution": [
    [
      [
        0,
        7
      ],
      [
        0,
        6
      ]
    ],
    [
      [
        0,
        0
      ],
      [
        0,
        1
      ]
    ],
    [
      [
        0,
        2
      ],
      [
        0,
        3
      ]
    ],
    [
      [
        0,
        5
      ],
      [
        0,
        4
      ]
    ]
  ]
}
